config.py
server.py
common/__init__.py
common/auth/__init__.py
common/auth/authentication_manager.py
common/auth/token_cache.py
common/core/__init__.py
common/core/base_adapter.py
common/core/base_service.py
common/domain/__init__.py
common/domain/crn_validator.py
common/domain/default_session_store.py
common/domain/session_store.py
common/domain/session_store_protocol.py
common/models/__init__.py
common/models/error_models.py
data_ms/__init__.py
data_ms/adapters/__init__.py
data_ms/adapters/data_ms_adapter.py
data_ms/entities/__init__.py
data_ms/entities/service.py
data_ms/entities/tools.py
data_ms/records/__init__.py
data_ms/records/service.py
data_ms/records/tools.py
data_ms/search/__init__.py
data_ms/search/models.py
data_ms/search/service.py
data_ms/search/tool_models.py
data_ms/search/tools.py
data_ms/search/validators.py
ibm_mdm_mcp_server-1.0.10.dist-info/licenses/LICENSE
model_ms/__init__.py
model_ms/adapters/__init__.py
model_ms/adapters/model_ms_adapter.py
model_ms/model/__init__.py
model_ms/model/config.py
model_ms/model/exceptions.py
model_ms/model/formatters.py
model_ms/model/service.py
model_ms/model/tools.py
ibm_mdm_mcp_server-1.0.10.dist-info/METADATA
ibm_mdm_mcp_server-1.0.10.dist-info/WHEEL
ibm_mdm_mcp_server-1.0.10.dist-info/entry_points.txt
ibm_mdm_mcp_server-1.0.10.dist-info/top_level.txt
ibm_mdm_mcp_server-1.0.10.dist-info/RECORD
