Metadata-Version: 2.4
Name: ibm_mdm_mcp_server
Version: 1.0.10
Summary: A Model Context Protocol (MCP) server for IBM Master Data Management (MDM) services
Author-email: Najeeb Arif <najeeb.arif@ibm.com>, Muhammed Abdul Majeed Ameen <muhammed.abdul.majeed.ameen@ibm.com>
Maintainer-email: Najeeb Arif <najeeb.arif@ibm.com>, Muhammed Abdul Majeed Ameen <muhammed.abdul.majeed.ameen@ibm.com>
License: Apache-2.0
Project-URL: Homepage, https://github.com/IBM/mdm-mcp-server
Project-URL: Documentation, https://github.com/IBM/mdm-mcp-server/blob/main/README.md
Project-URL: Repository, https://github.com/IBM/mdm-mcp-server
Project-URL: Issues, https://github.com/IBM/mdm-mcp-server/issues
Project-URL: Changelog, https://github.com/IBM/mdm-mcp-server/blob/main/CHANGELOG.md
Keywords: mcp,model-context-protocol,ibm,mdm,master-data-management,match360,ai,claude,fastmcp
Classifier: Development Status :: 5 - Production/Stable
Classifier: Intended Audience :: Developers
Classifier: License :: OSI Approved :: Apache Software License
Classifier: Operating System :: OS Independent
Classifier: Programming Language :: Python :: 3
Classifier: Programming Language :: Python :: 3.10
Classifier: Programming Language :: Python :: 3.11
Classifier: Programming Language :: Python :: 3.12
Classifier: Topic :: Software Development :: Libraries :: Python Modules
Classifier: Topic :: Scientific/Engineering :: Artificial Intelligence
Classifier: Framework :: FastAPI
Requires-Python: >=3.10
License-File: LICENSE
Requires-Dist: fastmcp>=2.14.0
Requires-Dist: fastapi>=0.121.0
Requires-Dist: uvicorn>=0.38.0
Requires-Dist: pydantic>=2.12.0
Requires-Dist: pydantic-settings>=2.12.0
Requires-Dist: python-dotenv>=1.2.0
Requires-Dist: requests>=2.32.0
Requires-Dist: httpx>=0.28.0
Requires-Dist: PyJWT>=2.10.0
Requires-Dist: urllib3>=2.6.3
Requires-Dist: Authlib>=1.6.5
Provides-Extra: dev
Requires-Dist: pytest>=8.3.0; extra == "dev"
Requires-Dist: pytest-cov>=6.0.0; extra == "dev"
Requires-Dist: pytest-mock>=3.14.0; extra == "dev"
Dynamic: license-file
